Semi Finals/4to2PriorityEncoder.v
module priority_encoder_4to2(
    input wire [3:0] in,
    output reg [2:0] out
);

    always @* begin
        case(1'b1)
            in[3]: out = 3'b111;
            in[2]: out = 3'b101;
            in[1]: out = 3'b011;
			in[0]: out = 3'b001;
			default: out = 3'bxx0;
        endcase
    end

endmodule

module priority_encoder_4to2_tb;

    reg [3:0] in;
    wire [2:0] out;

    // Instantiate the DUT
    priority_encoder_4to2 uut (
        .in(in),
        .out(out)
    );

    initial begin
		$dumpfile("4to2.vcd");
        $dumpvars(0, priority_encoder_4to2_tb);
	end
	initial begin
		in = 4'b0000;
        #3 
		in = 4'b0001;
        #3 
		in = 4'b0010;
        #3 
		in = 4'b0100;
        #3 
		in = 4'b0101;
		#3 
		in = 4'b0110;
		#3
		in = 4'b0111;
		#3
		in = 4'b1000;
		#3
		in = 4'b1001;
		#3
		in = 4'b1010;
		#3
		in = 4'b1011;
		#3
		in = 4'b1100;
		#3
		in = 4'b1101;
		#3
		in = 4'b1110;
		#3
		in = 4'b1111;
		#3
       $finish;
    end
endmodule

Semi Finals/4to2.vcd
$date
	Fri May 23 01:18:27 2025
$end
$version
	Icarus Verilog
$end
$timescale
	1s
$end
$scope module priority_encoder_4to2_tb $end
$var wire 3 ! out [2:0] $end
$var reg 4 " in [3:0] $end
$scope module uut $end
$var wire 4 # in [3:0] $end
$var reg 3 $ out [2:0] $end
$upscope $end
$upscope $end
$enddefinitions $end
#0
$dumpvars
bx0 $
b0 #
b0 "
bx0 !
$end
#3
b1 !
b1 $
b1 "
b1 #
#6
b11 !
b11 $
b10 "
b10 #
#9
b101 !
b101 $
b100 "
b100 #
#12
b101 "
b101 #
#15
b110 "
b110 #
#18
b111 "
b111 #
#21
b111 !
b111 $
b1000 "
b1000 #
#24
b1001 "
b1001 #
#27
b1010 "
b1010 #
#30
b1011 "
b1011 #
#33
b1100 "
b1100 #
#36
b1101 "
b1101 #
#39
b1110 "
b1110 #
#42
b1111 "
b1111 #
