Semi Finals/1bitALU.v
module Sigbin(x,s,R);
	input [1:0]x;
	input [1:0]s;
	output reg R;
	
always @ (*) begin
    case(s)
      2'b00: R = x[0] ^ x[1];  // Addition
      2'b01: R = x[0] ^ x[1];  // Subtraction, assuming borrowing is not considered
      2'b10: R = x[0] & x[1];  // Bitwise AND
      2'b11: R = x[0] || x[1];  // Bitwise OR
      default: R = 0;
    endcase
  end
 
	
endmodule

module Sigbin_stimulus_generator(x,S);
	output reg [1:0]x;
	output reg [1:0]S;
	initial
	begin
		
		S=3'b000;
		x=2'b00;
		
		
		$dumpfile("alu.vcd");
		$dumpvars;
		
		
		S=2'b00; x=2'b00; 
		#3
		S=2'b00; x=2'b01; 
		#3
		S=2'b00; x=2'b10; 
		#3
		S=2'b00; x=2'b11; 
		#3
	
		S=2'b01; x=2'b00; 
		#3
		S=2'b01; x=2'b01; 
		#3
		S=2'b01; x=2'b10; 
		#3
		S=2'b01; x=2'b11; 
		#3
		
		S=2'b10; x=2'b00;
		#3
		S=2'b10; x=2'b01;
		#3
		S=2'b10; x=2'b10;
		#3
		S=2'b10; x=2'b11;
		
		#3
		S=2'b11; x=2'b00;
		#3
		S=2'b11; x=2'b01;
		#3
		S=2'b11; x=2'b10;
		#3
		S=2'b11; x=2'b11;
		#3
		
		$finish;
	end
endmodule

module Sigbin_testbench();
	wire [1:0]s;
	wire [1:0]x;
	
	Sigbin arithmeticOps(x,s,R);
	Sigbin_stimulus_generator arithmetic(x,s);
endmodule

Semi Finals/alu.vcd
$date
	Fri May 23 01:03:26 2025
$end
$version
	Icarus Verilog
$end
$timescale
	1s
$end
$scope module Sigbin_testbench $end
$var wire 2 ! x [1:0] $end
$var wire 2 " s [1:0] $end
$var wire 1 # R $end
$scope module arithmetic $end
$var reg 2 $ S [1:0] $end
$var reg 2 % x [1:0] $end
$upscope $end
$scope module arithmeticOps $end
$var wire 2 & s [1:0] $end
$var wire 2 ' x [1:0] $end
$var reg 1 # R $end
$upscope $end
$upscope $end
$enddefinitions $end
#0
$dumpvars
b0 '
b0 &
b0 %
b0 $
0#
b0 "
b0 !
$end
#3
1#
b1 !
b1 %
b1 '
#6
b10 !
b10 %
b10 '
#9
0#
b11 !
b11 %
b11 '
#12
b0 !
b0 %
b0 '
b1 "
b1 $
b1 &
#15
1#
b1 !
b1 %
b1 '
#18
b10 !
b10 %
b10 '
#21
0#
b11 !
b11 %
b11 '
#24
b0 !
b0 %
b0 '
b10 "
b10 $
b10 &
#27
b1 !
b1 %
b1 '
#30
b10 !
b10 %
b10 '
#33
1#
b11 !
b11 %
b11 '
#36
0#
b0 !
b0 %
b0 '
b11 "
b11 $
b11 &
#39
1#
b1 !
b1 %
b1 '
#42
b10 !
b10 %
b10 '
#45
b11 !
b11 %
b11 '
