Semi Finals/3x8Decoder.v
module decoder(
    input [2:0] input_bits,
    output reg [7:0] output_bits
);

always @*
begin
    if(input_bits == 3'b000)
        output_bits = 8'b00000001;
    else if(input_bits == 3'b001)
        output_bits = 8'b00000010;
    else if(input_bits == 3'b010)
        output_bits = 8'b00000100;
    else if(input_bits == 3'b011)
        output_bits = 8'b00001000;
    else if(input_bits == 3'b100)
        output_bits = 8'b00010000;
    else if(input_bits == 3'b101)
        output_bits = 8'b00100000;
    else if(input_bits == 3'b110)
        output_bits = 8'b01000000;
    else
        output_bits = 8'b10000000;
end

endmodule

module testbench_decoder_3x8;

reg [2:0] input_bits;
wire [7:0] output_bits;

decoder uut (
    .input_bits(input_bits),
    .output_bits(output_bits)
);

initial begin
    $dumpfile("decoder.vcd");
    $dumpvars(0, testbench_decoder_3x8);

	input_bits = 3'b000;
    #3;
	input_bits = 3'b001;
    #3;
	input_bits = 3'b010;
    #3;
	input_bits = 3'b011;
    #3;
    input_bits = 3'b100;
    #3;
    input_bits = 3'b101;
    #3;
    input_bits = 3'b110;
    #3;
    input_bits = 3'b111;
    #3;

    $finish;
end

endmodule

Semi Finals/decoder.vcd
$date
	Fri May 23 01:20:29 2025
$end
$version
	Icarus Verilog
$end
$timescale
	1s
$end
$scope module testbench_decoder_3x8 $end
$var wire 8 ! output_bits [7:0] $end
$var reg 3 " input_bits [2:0] $end
$scope module uut $end
$var wire 3 # input_bits [2:0] $end
$var reg 8 $ output_bits [7:0] $end
$upscope $end
$upscope $end
$enddefinitions $end
#0
$dumpvars
b1 $
b0 #
b0 "
b1 !
$end
#3
b10 !
b10 $
b1 "
b1 #
#6
b100 !
b100 $
b10 "
b10 #
#9
b1000 !
b1000 $
b11 "
b11 #
#12
b10000 !
b10000 $
b100 "
b100 #
#15
b100000 !
b100000 $
b101 "
b101 #
#18
b1000000 !
b1000000 $
b110 "
b110 #
#21
b10000000 !
b10000000 $
b111 "
b111 #
